{
  "arch": "x86_64",
  "auth": null,
  "build": "0",
  "build_number": 0,
  "channel": "https://conda.anaconda.org/cyclus/linux-64",
  "depends": [],
  "files": [
    "lib/libffi-3.0.13/include/ffi.h",
    "lib/libffi-3.0.13/include/ffitarget.h",
    "lib/libffi.a",
    "lib/libffi.la",
    "lib/libffi.so",
    "lib/libffi.so.6",
    "lib/libffi.so.6.0.1",
    "lib/pkgconfig/libffi.pc",
    "share/info/dir",
    "share/info/libffi.info",
    "share/man/man3/ffi.3",
    "share/man/man3/ffi_call.3",
    "share/man/man3/ffi_prep_cif.3",
    "share/man/man3/ffi_prep_cif_var.3"
  ],
  "fn": "libffi-3.0.13-0.tar.bz2",
  "license": "Eclipse Public License 1.0",
  "link": {
    "source": "/home/PERSONALE/eugenio.fonzi2/miniconda3/pkgs/libffi-3.0.13-0",
    "type": 1
  },
  "md5": "5a7c27bfa41257753c8d4e498e4908cb",
  "name": "libffi",
  "noarch": null,
  "platform": "linux",
  "preferred_env": null,
  "priority": 1,
  "requires": [],
  "schannel": "cyclus",
  "size": 45886,
  "subdir": "linux-64",
  "url": "https://conda.anaconda.org/cyclus/linux-64/libffi-3.0.13-0.tar.bz2",
  "version": "3.0.13",
  "with_features_depends": {}
}